tests/__init__.py
tests/test_sanity.py
tests/test_tools.py
tinylang/__init__.py
tinylang/history/__init__.py
tinylang/history/chat.py
tinylang/llms/__init__.py
tinylang/llms/base.py
tinylang/llms/claude.py
tinylang/llms/gemini.py
tinylang/llms/openai.py
tinylang/llms/util.py
tinylang/tools/__init__.py
tinylang/tools/tool.py
tinylang-4.3.0.dist-info/LICENSE
tinylang-4.3.0.dist-info/METADATA
tinylang-4.3.0.dist-info/WHEEL
tinylang-4.3.0.dist-info/top_level.txt
tinylang-4.3.0.dist-info/RECORD
