Metadata-Version: 2.1
Name: tinylang
Version: 4.3.0
Summary: A tiny language interpreter
License-File: LICENSE
Requires-Dist: annotated-types ==0.5.0
Requires-Dist: anthropic ==0.29.0
Requires-Dist: anyio ==3.7.1
Requires-Dist: cachetools ==5.3.3
Requires-Dist: certifi ==2023.7.22
Requires-Dist: charset-normalizer ==3.3.2
Requires-Dist: distro ==1.8.0
Requires-Dist: filelock ==3.15.4
Requires-Dist: fsspec ==2024.6.0
Requires-Dist: google-ai-generativelanguage ==0.6.5
Requires-Dist: google-api-core[grpc] ==2.19.0
Requires-Dist: google-api-python-client ==2.134.0
Requires-Dist: google-auth ==2.30.0
Requires-Dist: google-auth-httplib2 ==0.2.0
Requires-Dist: google-generativeai ==0.7.0
Requires-Dist: googleapis-common-protos ==1.63.1
Requires-Dist: grpcio ==1.64.1
Requires-Dist: grpcio-status ==1.62.2
Requires-Dist: h11 ==0.14.0
Requires-Dist: httpcore ==1.0.1
Requires-Dist: httplib2 ==0.22.0
Requires-Dist: httpx ==0.25.1
Requires-Dist: huggingface-hub ==0.23.4
Requires-Dist: idna ==3.4
Requires-Dist: jiter ==0.4.2
Requires-Dist: openai ==1.35.3
Requires-Dist: packaging ==24.1
Requires-Dist: proto-plus ==1.24.0
Requires-Dist: protobuf ==4.25.3
Requires-Dist: pyasn1 ==0.6.0
Requires-Dist: pyasn1-modules ==0.4.0
Requires-Dist: pydantic ==2.4.2
Requires-Dist: pydantic-core ==2.10.1
Requires-Dist: pyparsing ==3.1.2
Requires-Dist: python-dotenv ==1.0.1
Requires-Dist: pyyaml ==6.0.1
Requires-Dist: requests ==2.32.3
Requires-Dist: rsa ==4.9
Requires-Dist: sniffio ==1.3.0
Requires-Dist: tokenizers ==0.19.1
Requires-Dist: tqdm ==4.66.1
Requires-Dist: typing-extensions ==4.8.0
Requires-Dist: uritemplate ==4.1.1
Requires-Dist: urllib3 ==2.2.2
